Workbook

Sheet JANEIRO
A1: MUDANÇAS DBR - JANEIRO
A3: RECEITAS | I3: RECEITAS A RECEBER - MÊS ANTERIOR
A4: Data | B4: Tipo | C4: Valor | D4: Recebido | E4: A receber | F4: cliente | G4: Imposto | I4: Data | J4: Tipo | K4: Valor | L4: Recebido | M4: A receber | N4: cliente | O4: Status
A5: 46024 | B5: Local | C5: 2000 | D5: 2000 | E5: =C5-D5 -> 0 | F5: Elcimara | I5: 45979 | J5: Inter | K5: 8760 | L5: 7008 | M5: =K5-L5 -> 1752 | N5: José Carlos | O5: pago
A6: 46027 | B6: Local | C6: 3500 | D6: 3500 | E6: =C6-D6 -> 0 | F6: Alexandre | I6: 45988 | J6: Inter | K6: 34240 | L6: 27392 | M6: 6848 | N6: Flávia
A7: 46028 | B7: Local | C7: 2000 | D7: 2000 | E7: =C7-D7 -> 0 | F7: André | I7: 46006 | J7: Inter | K7: 10745 | L7: 8596 | M7: =K7-L7 -> 2149 | N7: Wadson
A8: 46028 | B8: Papel Couro | C8: 60 | D8: 60 | E8: =C8-D8 -> 0 | F8: Papel Couro | I8: 46007 | J8: Inter | K8: 10855 | L8: 8684 | M8: =K8-L8 -> 2171 | N8: Larissa
A9: 46029 | B9: Local | C9: 4000 | D9: 4000 | E9: =C9-D9 -> 0 | F9: Viviane | I9: 46002 | J9: Inter | K9: 24800 | L9: 20380 | M9: =K9-L9 -> 4420 | N9: Dom | O9: pago
A10: 46029 | B10: Caixas | C10: 24 | D10: 24 | E10: =C10-D10 -> 0 | F10: Caixas | I10: 46052 | J10: Inter | M10: 320 | N10: Maria 1x2
A11: 46029 | B11: Local | C11: 5500 | D11: 5500 | E11: =C11-D11 -> 0 | F11: Igreja Adv | I11: 46013 | J11: Inter | K11: 10740 | L11: 8592 | M11: =K11-L11 -> 2148 | N11: Falcão
A12: 46030 | B12: Caixas | C12: 48 | D12: 48 | E12: =C12-D12 -> 0 | F12: Caixas | K12: =SUM(K5:K9) -> 89400 | L12: =SUM(L5:L9) -> 72060 | M12: =SUM(M5:M11) -> 19808
A13: 46031 | B13: Local | C13: 2500 | D13: 2500 | E13: =C13-D13 -> 0 | F13: Adão
A14: 46034 | B14: Inter | C14: 12200 | E14: =C14-D14 -> 12200 | F14: Diosélia | G14: Pagto 07/02
A15: 46034 | B15: Veiculo | C15: 5000
A16: 46035 | B16: Local | C16: 2000 | D16: 2000 | E16: =C16-D16 -> 0 | F16: Jaqueline
A17: 46036 | B17: Caixas | C17: 8937.5 | D17: 8937.5 | E17: =C17-D17 -> 0 | F17: Rafael
A18: 46037 | B18: Local | C18: 1900 | D18: 1900 | E18: =C18-D18 -> 0 | F18: João Victor
A19: 46037 | B19: Frete | C19: 500 | D19: 500 | E19: =C19-D19 -> 0 | F19: Tiago
A20: 46040 | B20: Local | C20: 2000 | D20: 2000 | E20: =C20-D20 -> 0 | F20: Júlio
A21: 46041 | B21: Inter | C21: 8440 | D21: 5600 | E21: =C21-D21 -> 2840 | F21: Ketlen
A22: 46041 | B22: Local | C22: 2200 | D22: 2200 | E22: =C22-D22 -> 0 | F22: Vagalume
A23: 46042 | B23: Inter | C23: 7700 | D23: 6160 | E23: =C23-D23 -> 1540 | F23: Lucimara
A24: 46044 | B24: Local | C24: 2800 | D24: 2800 | E24: =C24-D24 -> 0 | F24: Bernardo
A25: 46048 | B25: Guarda-móveis | C25: 700 | D25: 700 | F25: Flávio
A26: 46049 | B26: Local | C26: 2700 | E26: =C26-D26 -> 2700 | F26: João
A27: 46052 | B27: Local | C27: 1500 | D27: 1500 | E27: - | F27: Mayara
C28: =SUM(C5:C27) -> 78209.5 | D28: 51729.5 | E28: 25780 | G28: -
A30: DESPESAS com Pessoal - Díária
A31: Data | B31: Tipo | C31: Valor
A32: 46024 | B32: Diária | C32: 1000
A33: 46027 | B33: Diária | C33: 1000
A34: 46028 | B34: Diária | C34: 1000
A35: 46029 | B35: Diária | C35: 1000
A36: 46031 | B36: Diária | C36: 1000
A37: 46034 | B37: Diária | C37: =200*4 -> 800
A38: 46035 | B38: Diária | C38: 1000
A39: 46036 | B39: Diária | C39: =200*4 -> 800
A40: 46037 | B40: Diária | C40: 1000
A41: 46040 | B41: Diária | C41: 1000
A42: 46041 | B42: Diária | C42: 1000
A43: 46042 | B43: Diária | C43: 1000
A44: 46044 | B44: Diária | C44: 1000
A45: 46045 | B45: Diária | C45: 1000
A46: 46049 | B46: Diária | C46: 1000
A47: 46052 | B47: Diária | C47: 1000
C48: =SUM(C32:C47) -> 15600
A50: DESPESAS com Pessoal - Alimentação
A51: Data | B51: Tipo | C51: Valor | D51: Status
A52: 46024 | B52: Almoço | C52: 110
A53: 46027 | B53: Almoço | C53: 110
A54: 46028 | B54: Almoço | C54: 110
A55: 46029 | B55: Almoço | C55: 110
A56: 46031 | B56: Almoço | C56: 110
A57: 46034 | B57: Almoço | C57: 90
A58: 46035 | B58: Almoço | C58: 110
A59: 46036 | B59: Almoço | C59: 90
A60: 46037 | B60: Almoço | C60: 110
A61: 46040 | B61: Almoço | C61: 110
A62: 46041 | B62: Almoço | C62: 110
A63: 46042 | B63: Almoço | C63: 110
... A67: 46052 | B67: Almoço | C67: 110
C68: =SUM(C52:C67) -> 1720
A70: DESPESAS
A71: MATÉRIA - PRIMA
A72: Data | B72: Tipo | C72: Valor | D72: Pagto
A73: 46030 | B73: Caixas | C73: 1174.1 | D73: Pago
A74: 46035 | B74: Plástico Bolha | C74: 1290 | D74: Pago
A75: 46041 | B75: Caixas | C75: 1269.3 | D75: pago
C76: =SUM(C72:C75) -> 3733.4
A78: COMPRAS - DIVERSAS
A79: Data | B79: Tipo | C79: Valor | D79: Pagto
A80: 46031 | B80: Ar condic | C80: 6300 | D80: Pago
C81: =SUM(C80:C80) -> 6300
A83: DESPESAS FIXAS - CONTAS A PAGAR
A84: Data | B84: Tipo | C84: Valor | D84: Status
A85: 46023 | B85: ALUGUEL | C85: 2212 | D85: Pago
A86: 46023 | B86: IPTU | C86: 86.31 | D86: Pago
A87: 46023 | B87: Água | C87: 136.56 | D87: Pago
A88: 46025 | B88: Trafego Pago | C88: 1000 | D88: Pago
A89: 46027 | B89: MASTER FOCO | C89: 1580 | D89: Pago
A90: 46030 | B90: BSOFT | C90: 153.26 | D90: Pago
A91: 46032 | B91: LUZ | C91: 251.55 | D91: Pago
A92: 46034 | B92: Ellen - Contadora | C92: 400 | D92: Pago
A93: 46037 | B93: SEGURO | C93: 644.28 | D93: Pago
A94: 46039 | B94: NET | C94: 409.9 | D94: Pago
A95: 46040 | B95: Parc Banco | C95: 941.6 | D95: Pago
A96: 46042 | B96: DAS | C96: 1691.83 | D96: Pago
A97: 46052 | B97: Parc DAS | C97: 485.76
A98: 46052 | B98: SAMMYA | C98: 2000 | D98: Pago
A99: 46052 | B99: Uber | C99: 313.8
A100: 46052 | B100: Pro labore | C100: =C28*10% -> 7820.95
C101: =SUM(C85:C100) -> 20127.8
A103: DESPESAS - FRETE
A104: Data | B104: Tipo | C104: Valor | D104: Status
A105: 46027 | C105: 9100 | E105: Larissa/Dom
A106: 46028 | C106: 4900
A107: 46041 | C107: 4550 | E107: Wadson
C108: =SUM(C105:C107) -> 18550
B111: RECEITAS | C111: =C28 -> 78209.5
B112: DESPESAS | C112: =C48+C76+C81+C101+C108 -> 64311.2
...

Sheet FEVEREIRO
A1: MUDANÇAS DBR - FEVEREIRO
A3: RECEITAS | I3: RECEITAS A RECEBER - MÊS ANTERIOR
A4: Data | B4: Tipo | C4: Valor | D4: Recebido | E4: A receber | F4: cliente | I4: Data | J4: Tipo | K4: Valor | L4: Recebido | M4: A receber | N4: cliente | O4: Status
A5: 46055 | B5: Inter | C5: 22550 | D5: 22550 | F5: Priscila | I5: 45988 | J5: Inter | K5: 34240 | L5: 32392 | M5: 1848 | N5: Flávia
A6: 46057 | B6: Inter | C6: 17880 | D6: 17880 | F6: Jeferson | I6: 46006 | J6: Inter | K6: 10745 | L6: 10745 | M6: - | N6: Wadson | O6: 46055
A7: 46057 | B7: Veiculo | C7: 5000 | D7: 5000 | I7: 46052 | J7: Inter | M7: - | N7: Maria 1x2
A8: 46059 | B8: Local | C8: 3000 | D8: 3000 | F8: Fabiano/Mayara | I8: 46013 | J8: Inter | K8: 10740 | L8: 10740 | M8: - | N8: Falcão | O8: 46062
A9: 46057 | B9: Caixas | C9: 60 | D9: 60 | F9: Line Produções | I9: 46034 | J9: Inter | K9: 17200 | L9: 17200 | M9: - | N9: Diosélia | O9: 46059
A10: 46063 | B10: Local | C10: 24000 | D10: 12000 | E10: 12000 | F10: Rodolfo | I10: 46041 | J10: Inter | K10: 8440 | L10: 7040 | M10: 1400 | N10: Ketlen
A11: 46072 | B11: Local | C11: 1400 | D11: 1400 | F11: Andrea | I11: 46042 | J11: Inter | K11: 7700 | L11: 6160 | M11: 1540 | N11: Lucimara
A12: 46073 | B12: Local | C12: 1800 | D12: 1800 | F12: Tays | M12: 4788
A13: 46076 | B13: Caixas | C13: 108 | D13: 108 | F13: Facebook
A14: 46076 | B14: Caixas | C14: 68 | D14: 68 | F14: Facebook
A15: 46077 | B15: Local | C15: 3250 | D15: 3250 | F15: Joana
A16: 46077 | B16: Caixas | C16: 55 | D16: 55 | F16: Facebook
A17: 46078 | B17: Veiculo | C17: 5200 | D17: 5200 | F17: Lisandro
A18: 46078 | B18: Local | C18: 3200 | D18: 3200 | F18: Luiz
A19: 46079 | B19: Inter | C19: 9710 | D19: 9710 | F19: Alexandre
A20: 46079 | B20: Local | C20: 2000 | D20: 2000 | F20: Tiago
A21: 46080 | B21: Local | C21: 6000 | D21: 8000 | F21: Tiago
C22: =SUM(C5:C21) -> 105281 | D22: =SUM(D5:D21) -> 95281 | E22: =SUM(E5:E21) -> 12000
A25: DESPESAS com Diária
A26: Data | B26: Tipo | C26: Valor | D26: Status
A27: 46055 | B27: Diária | C27: 1000
A28: 46057 | B28: Diária | C28: 1000
A29: 46057 | B29: Diária | C29: 1000
A30: 46059 | B30: Diária | C30: 1000
A31: 46057 | B31: Diária | C31: 1000
A32: 46063 | B32: Diária | C32: 1000
A33: 46072 | B33: Diária | C33: 1000
A34: 46073 | B34: Diária | C34: 1000
A35: 46076 | B35: Diária | C35: 1000
A36: 46076 | B36: Diária | C36: 1000
A37: 46077 | B37: Diária | C37: 1000
A38: 46077 | B38: Diária | C38: 1000
... A43: 46080 | B43: Diária | C43: 1000
C44: =SUM(C27:C43) -> 17000
A46: DESPESAS com Diária
A47: Data | B47: Tipo | C47: Valor | D47: Status
A48: 46055 | B48: Almoço | C48: 110
A49: 46057 | B49: Almoço | C49: 110
A50: 46057 | B50: Almoço | C50: 110
A51: 46059 | B51: Almoço | C51: 110
A52: 46057 | B52: Almoço | C52: 110
A53: 46063 | B53: Almoço | C53: 110
A54: 46072 | B54: Almoço | C54: 110
A55: 46073 | B55: Almoço | C55: 110
A56: 46076 | B56: Almoço | C56: 110
A57: 46076 | B57: Almoço | C57: 110
A58: 46077 | B58: Almoço | C58: 110
A59: 46077 | B59: Almoço | C59: 110
... A64: 46080 | B64: Almoço | C64: 110
C65: =SUM(C48:C64) -> 1870
A67: MATÉRIA - PRIMA
A68: Data | B68: Tipo | C68: Valor | D68: Pagto
A69: 46079 | B69: Fita/Stretch | C69: 1798.4 | D69: Pago
C76: =SUM(C68:C75) -> 1798.4
A78: COMPRAS - DIVERSAS
A79: Data | B79: Tipo | C79: Valor | D79: Pagto
A80: 46062 | B80: Manut Palio | C80: 2480 | D80: Pago
A81: 46071 | B81: Manut Palio | C81: 598 | D81: Pago
C87: =SUM(C80:C86) -> 3078
A89: DESPESAS FIXAS - CONTAS A PAGAR
A90: Data | B90: Tipo | C90: Valor | D90: Status
A91: 46023 | B91: ALUGUEL | C91: 2212 | D91: Pago
A92: 46025 | B92: Trafego Pago | C92: 1000 | D92: Pago
A93: 46027 | B93: MASTER FOCO | C93: 1580 | D93: Pago
A94: 46030 | B94: BSOFT | C94: 153.26 | D94: Pago
A95: 46032 | B95: LUZ | C95: 251.55 | D95: Pago
A96: 46034 | B96: Ellen - Contadora | C96: 400 | D96: Pago
A97: 46037 | B97: SEGURO 12/25 | C97: 644.28 | D97: Pago
A98: 46039 | B98: NET | C98: 409.9
A99: 46040 | B99: Parc Banco | C99: 941.6 | D99: Pago
A100: 46073 | B100: DAS | D100: Pago
A101: 46052 | B101: Parc DAS | C101: 485.76
A102: 46052 | B102: SAMMYA | C102: 3000
A103: 29/02/2026 | B103: Uber | C103: 394.46
A104: 46052 | B104: Pro labore | C104: =C22*10% -> 10528.1
C105: =SUM(C91:C104) -> 22000.91
A107: DESPESAS - FRETE
A108: Data | B108: Tipo | C108: Valor | D108: Status
A109: 46054 | C109: =10*350 -> 3500 | D109: Ketlen
A110: 46054 | C110: =15*350 -> 5250 | D110: Diosélia
A111: 46054 | C111: =10*350 -> 3500 | D111: Lucimara
A112: 46058 | C112: =31*350 -> 10850 | D112: Jeferson
C113: =SUM(C109:C112) -> 23100
B119: RECEITAS | C119: =C22 -> 105281
B120: DESPESAS | C120: =C44+C65+C76+C87+C105+C113 -> 68847.31
B121: Lucro | C121: =C119-C120 -> 36433.69
B122: Davis | C122: =C104+C121 -> 46961.79

Sheet MARÇO
A1: MUDANÇAS DBR - MARÇO
A3: RECEITAS | I3: RECEITAS A RECEBER - MÊS ANTERIOR
A4: Data | B4: Tipo | C4: Valor | D4: Recebido | E4: A receber | F4: cliente | G4: Imposto | I4: Data | J4: Tipo | K4: Valor | L4: Recebido | M4: A receber | N4: cliente | O4: Status
A5: 46083 | B5: Local | C5: 2475 | D5: 2475 | F5: Bruno | I5: 45988 | J5: Inter | K5: 34240 | L5: 32392 | M5: 1848 | N5: Flávia
A6: 46084 | B6: Local | C6: 2750 | D6: 2750 | F6: Gilmara | I6: 46041 | J6: Inter | K6: 8440 | L6: 8440 | M6: - | N6: Ketlen | O6: 46100
A7: 46085 | B7: Local | C7: 3375 | D7: 3375 | F7: Fernando | I7: 46042 | J7: Inter | K7: 7700 | L7: 7700 | M7: - | N7: Lucimara | O7: 46105
A8: 46086 | B8: Local | C8: 3375 | D8: 3375 | F8: Fernando | I8: 46063 | J8: Local | K8: 24000 | L8: 12000 | M8: 12000 | N8: Rodolfo
A9: 46087 | B9: Inter | C9: 15112 | D9: 15112 | F9: João | I9: 46079 | J9: Inter | K9: 9710 | L9: 9710 | M9: - | N9: Alexandre | O9: Pg 02/03 e 30/03
A10: 46090 | B10: Local | C10: 2000 | D10: 2000 | F10: Alline | I10: 46078 | J10: Local | K10: 3200 | L10: 3200 | N10: Luiz Fernando | O10: Pg 11/03
A11: 46093 | B11: Local | C11: 2675 | D11: 2675 | F11: Mayanne | M11: 13848
A12: 46097 | B12: Local | C12: 2000 | D12: 2000 | F12: Flávio
A13: 46097 | B13: Caixas | C13: 36 | D13: 36 | F13: Facebook
A14: 46097 | B14: Caixas | C14: 18 | D14: 18 | F14: Facebook
A15: 46099 | B15: Local | C15: 2500 | D15: 2500 | F15: Silvio
A16: 46104 | B16: Local | C16: 4250 | D16: 4250 | F16: Paul
A17: 46104 | B17: Local | C17: 8250 | D17: 8100.9 | F17: Alexandre | G17: Cartão
A18: 46105 | B18: Local | C18: 3750 | D18: 3750 | F18: Jonival
A19: 46106 | B19: Local | C19: 2000 | D19: 2000 | F19: Regina
A20: 46107 | B20: Frete | C20: 1200 | D20: 1200 | F20: Bruno
A21: 46108 | B21: Local | C21: 2750 | D21: 2750 | F21: Samuel
A22: 46110 | B22: Local | C22: 2000 | D22: 2000 | F22: Raphael
A23: 46107 | B23: Inter | C23: 52250 | D23: 52250 | F23: Beatriz
A24: 46111 | B24: Local | C24: 2000 | D24: 2000 | F24: Orquidea
C25: =SUM(C5:C24) -> 114766 | D25: =SUM(D5:D24) -> 114616.9 | E25: =C25-D25 -> 149.1 | G25: =SUM(G20:G24) -> 0
A28: DESPESAS com Pessoal
A29: Data | B29: Tipo | C29: Valor | D29: Status
A30: 46083 | B30: Alimentação | C30: 110
A31: 46083 | B31: Diária | C31: 1000
A32: 46083 | B32: Nova Era | C32: 140.79
A33: 46084 | B33: Alimentação | C33: 110
A34: 46084 | B34: Diária | C34: 1000
A35: 46085 | B35: Alimentação | C35: 110
A36: 46085 | B36: Diária | C36: 1000
A37: 46086 | B37: Alimentação | C37: 110
A38: 46086 | B38: Diária | C38: 1000
A39: 46087 | B39: Alimentação | C39: 110
A40: 46087 | B40: Diária | C40: 1000
A41: 46090 | B41: Alimentação | C41: 110
... A64: 46111 | B64: Diária | C64: 1000
C65: =SUM(C30:C64) -> 20230.86
A68: DESPESAS
A69: MATÉRIA - PRIMA
A70: Data | B70: Tipo | C70: Valor | D70: Pagto
A71: 46104 | B71: Mat Embalagem | C71: 1350 | D71: Pago
C74: =SUM(C70:C73) -> 1350
A76: COMPRAS - DIVERSAS
A77: Data | B77: Tipo | C77: Valor | D77: Pagto
A78: 46097 | B78: Agua | C78: 24 | D78: PIX
A79: 46108 | B79: Agua | C79: 24 | D79: PIX
A80: 46097 | B80: Tintas | C80: 264 | D80: Pago
A81: 46093 | B81: Kit Porta | C81: 123 | D81: pago
C85: =SUM(C78:C84) -> 435
A87: DESPESAS FIXAS - CONTAS A PAGAR
A88: Data | B88: Tipo | C88: Valor | D88: Status
A89: 46082 | B89: ALUGUEL | C89: 2212 | D89: Pago
A90: 46084 | B90: Trafego Pago | C90: 1000 | D90: Pago
A91: 46086 | B91: MASTER FOCO | C91: 1580 | D91: Pago
A92: 46089 | B92: BSOFT | C92: 153.26 | D92: Pago
A93: 46091 | B93: LUZ | C93: 251.55 | D93: Pago
A94: 46093 | B94: Ellen - Contadora | C94: 400 | D94: Pago
A95: 46096 | B95: SEGURO 12/25 | C95: 644.28 | D95: Pago
A96: 46098 | B96: NET | C96: 409.9
A97: 46099 | B97: Parc Banco | C97: 941.6 | D97: Pago
A98: 46101 | B98: DAS | C98: 1448 | D98: Pago
A99: 46111 | B99: Parc DAS | C99: 485.76
A100: 46111 | B100: SAMMYA | C100: 3000
A101: 46111 | B101: Pro labore | C101: =C25*10% -> 11476.6
C102: =SUM(C89:C101) -> 24002.95
A104: DESPESAS - FRETE
A105: Data | B105: Tipo | C105: Valor | D105: Status
C111: =SUM(C106:C109) -> 0
B117: RECEITAS | C117: =C25 -> 114766
B118: DESPESAS | C118: =C74+C85+C102+C111+#REF! -> #REF!
B119: Lucro | C119: =C117-C118 -> #REF!
B120: Davis | C120: =C101+C119 -> #REF!

Sheet ABRIL
A1: MUDANÇAS DBR - ABRIL
A3: RECEITAS | I3: RECEITAS A RECEBER - MÊS ANTERIOR
A4: Data | B4: Tipo | C4: Valor | D4: Recebido | E4: A receber | F4: cliente | G4: Imposto | I4: Data | J4: Tipo | K4: Valor | L4: Recebido | M4: A receber | N4: cliente | O4: Status
A5: 46114 | B5: Inter | C5: 7000 | D5: 7000 | F5: Estivem | I5: 45988 | J5: Inter | K5: 34240 | L5: 32392 | M5: 1848 | N5: Flávia
A6: 46119 | B6: Caixas | C6: 6400 | D6: 6400 | F6: Rafael | I6: 46063 | J6: Local | K6: 24000 | L6: 24000 | M6: - | N6: Rodolfo
A7: 46122 | B7: Local | C7: 3500 | D7: 3500 | F7: Thays | M7: 1848
A8: 46125 | B8: Local | C8: 2500 | D8: 2500 | F8: Suelly
A9: 46127 | B9: Local | C9: 3500 | D9: 3500 | F9: Úrsula
A10: 46129 | B10: Local | C10: 2000 | D10: 2000 | F10: Giovani
A11: 46135 | B11: Local | C11: 2000 | D11: 2000 | F11: Eliane
A12: 46139 | B12: Local | C12: 2000 | D12: 2000 | F12: Caroline
C13: =SUM(C5:C12) -> 28900 | D13: =SUM(D5:D12) -> 28900 | E13: =C13-D13 -> 0
A16: DESPESAS com Pessoal
A17: Data | B17: Tipo | C17: Valor | D17: Status
A18: 46114 | B18: Alimentação | C18: 110
A19: 46114 | B19: Diária | C19: 1000
A20: 46119 | B20: Alimentação | C20: 110
A21: 46119 | B21: Diária | C21: 1000
A22: 46122 | B22: Alimentação | C22: 110
A23: 46122 | B23: Diária | C23: 1000
A24: 46125 | B24: Alimentação | C24: 110
A25: 46125 | B25: Diária | C25: 1000
A26: 46127 | B26: Alimentação | C26: 110
A27: 46127 | B27: Diária | C27: 1310
A28: 46128 | B28: Alimentação | C28: 110
A29: 46128 | B29: Diária | C29: 1000
... A37: 46139 | B37: Diária | C37: 1000
C38: =SUM(C18:C37) -> 11046 | D38: =SUM(D32:D37) -> 0 | E38: =C38-D38 -> 11046
A40: DESPESAS
A41: MATÉRIA - PRIMA
A42: Data | B42: Tipo | C42: Valor | D42: Pagto
C50: =SUM(C42:C49) -> 0
A52: COMPRAS - DIVERSAS
A53: Data | B53: Tipo | C53: Valor | D53: Pagto
A54: 46128 | B54: Água | C54: 24 | D54: PIX
A55: 46140 | B55: Água | C55: 24 | D55: PIX
A56: 46127 | B56: Alim mês | C56: 164.52 | D56: Pago
C61: =SUM(C54:C60) -> 212.52
A63: DESPESAS FIXAS - CONTAS A PAGAR
A64: Data | B64: Tipo | C64: Valor | D64: Status
A65: 46023 | B65: ALUGUEL | C65: 2212 | D65: Pago
A66: 46025 | B66: Trafego Pago | C66: 1000 | D66: Pago
A67: 46027 | B67: MASTER FOCO | C67: 1580 | D67: Pago
A68: 46030 | B68: BSOFT | C68: 153.26 | D68: Pago
A69: 46122 | B69: LUZ | C69: 181.06 | D69: Pago
A70: 46034 | B70: Ellen - Contadora | C70: 400
A71: 46037 | B71: SEGURO 12/25 | C71: 644.28 | D71: Pago
A72: 46039 | B72: NET | C72: 409.9
A73: 46040 | B73: Parc Banco | C73: 941.6
A74: 46132 | B74: DAS | C74: 2947.28 | D74: Pago
A75: 46132 | B75: Parc Alvará 02x26 | C75: 313.37 | D75: Pago
A76: 46142 | B76: Parc DAS 05x60 | C76: 506.99 | D76: Pago
A77: 46052 | B77: Milla | C77: 200
A78: 46052 | B78: SAMMYA | C78: 3000
A79: 46052 | B79: Pro labore | C79: =C13*10% -> 2890
C80: =SUM(C65:C79) -> 17379.74
A82: DESPESAS - FRETE
A83: Data | B83: Tipo | C83: Valor | D83: Status
C89: =SUM(C84:C87) -> 0
B95: RECEITAS | C95: =C13 -> 28900
B96: DESPESAS | C96: =C50+C61+C80+C89+#REF! -> #REF!
B97: Lucro | C97: =C95-C96 -> #REF!
B98: Davis | C98: =C79+C97 -> #REF!

Sheet MAIO
A1: MUDANÇAS DBR - MAIO
A3: RECEITAS | I3: RECEITAS A RECEBER - MÊS ANTERIOR
A4: Data | B4: Tipo | C4: Valor | D4: Recebido | E4: A receber | F4: cliente | G4: Imposto | I4: Data | J4: Tipo | K4: Valor | L4: Recebido | M4: A receber | N4: cliente | O4: Status
A5: 46149 | B5: Local | C5: 4000 | D5: 4000 | E5: - | F5: Jean | I5: 45988 | J5: Inter | K5: 34240 | L5: 32392 | M5: 1848 | N5: Flávia
A6: 46150 | B6: Local | C6: 2000 | D6: 2000 | E6: - | F6: Francisco
A7: 46153 | B7: Local | C7: 2000 | D7: 2000 | E7: - | F7: Domingos
A8: 46157 | B8: Local | C8: 2400 | D8: 2400 | E8: - | F8: William
A9: 46159 | B9: Local | C9: 36 | D9: 36 | E9: - | F9: Caixas
A10: 46160 | B10: Local | C10: 2500 | D10: 2500 | E10: - | F10: Romildo
A11: 46162 | B11: Local | C11: 3000 | D11: 3000 | E11: - | F11: Allyne
A12: 46164 | B12: Local | C12: 3500 | D12: 3500 | E12: - | F12: Bruna/Fabio
A13: 46169 | B13: Local | C13: 3500 | D13: 3500 | E13: - | F13: Adriana
A14: 46170 | B14: Inter | C14: =17994+1200 -> 19194 | D14: 14485.2 | E14: 4708.8 | F14: Janaina
A15: 46171 | B15: Local | C15: 2000 | D15: 2000 | E15: - | F15: Yuna
C16: =SUM(C5:C15) -> 44130 | D16: =SUM(D5:D15) -> 39421.2 | E16: =C16-D16 -> 4708.8
A19: DESPESAS COM PESSOAL - DIÁRIA
A20: Data | B20: Tipo | C20: Valor | D20: Status
A21: 46149 | B21: Diária | C21: 810
A22: 46150 | B22: Diária | C22: 810
A23: 46153 | B23: Diária | C23: 810
A24: 46157 | B24: Diária | C24: 810
A25: 46159 | B25: Diária | C25: 810
A26: 46160 | B26: Diária | C26: 810
A27: 46162 | B27: Diária | C27: 810
A28: 46164 | B28: Diária | C28: 810
A29: 46169 | B29: Diária | C29: 810
A30: 46170 | B30: Diária | C30: 810
A31: 46171 | B31: Diária | C31: 810
C32: =SUM(C21:C31) -> 8910
A34: DESPESAS COM PESSOAL - DIÁRIA
A35: Data | B35: Tipo | C35: Valor | D35: Status
A36: 46149 | B36: Almoço | C36: 115
A37: 46150 | B37: Almoço | C37: 115
A38: 46153 | B38: Almoço | C38: 115
A39: 46157 | B39: Almoço | C39: 115
A40: 46159 | B40: Almoço | C40: 115
A41: 46160 | B41: Almoço | C41: 115
A42: 46162 | B42: Almoço | C42: 115
A43: 46164 | B43: Almoço | C43: 115
A44: 46169 | B44: Almoço | C44: 115
A45: 46170 | B45: Almoço | C45: 115
A46: 46171 | B46: Almoço | C46: 115
C47: =SUM(C36:C46) -> 1265
A49: DESPESAS
A50: MATÉRIA - PRIMA
A51: Data | B51: Tipo | C51: Valor | D51: Pagto
C59: =SUM(C51:C58) -> 0
A61: COMPRAS - DIVERSAS
A62: Data | B62: Tipo | C62: Valor | D62: Pagto
A63: 46160 | B63: Água | C63: 24 | D63: PIX
C70: =SUM(C63:C69) -> 24
A72: DESPESAS FIXAS - CONTAS A PAGAR
A73: Data | B73: Tipo | C73: Valor | D73: Status
A74: 46023 | B74: ALUGUEL | C74: 2212 | D74: Pago
A75: 46025 | B75: Trafego Pago | C75: 1000 | D75: Pago
A76: 46027 | B76: MASTER FOCO | C76: 1580 | D76: Pago
A77: 46030 | B77: BSOFT | C77: 153.26 | D77: Pago
A78: 46152 | B78: LUZ | C78: 173.82 | D78: Pago
A79: 46034 | B79: Ellen - Contadora | C79: 400
A80: 46037 | B80: SEGURO 12/25 | C80: 644.28 | D80: Pago
A81: 46039 | B81: NET | C81: 409.9
A82: 46040 | B82: Parc Banco | C82: 941.6
A83: 46040 | B83: Parc Alvará - 03x26
A84: 46042 | B84: DAS | C84: 432.96 | D84: Pago
A85: 46052 | B85: Parc DAS - 06x60 | C85: 485.76
A86: 46052 | B86: SAMMYA | C86: 3000
A87: 46052 | B87: Pro labore | C87: =C16*10% -> 4413
C88: =SUM(C74:C87) -> 15846.58
A90: DESPESAS - FRETE
A91: Data | B91: Tipo | C91: Valor | D91: Status
A92: 46169 | B92: Frete | C92: 450 | D92: Pago
A93: 46144 | B93: Frete | C93: =10*350 -> 3500 | D93: Estivem
C94: =SUM(C92:C93) -> 3950
B100: RECEITAS | C100: =C16 -> 44130
B101: DESPESAS | C101: =C32+C47+C59+C70+C88+C94 -> 29995.58
B102: Lucro | C102: =C100-C101 -> 14134.42
B103: Davis | C103: =C87+C102 -> 18547.42

Sheet JUNHO
A1: MUDANÇAS DBR - JUNHO
A3: RECEITAS | I3: RECEITAS A RECEBER - MÊS ANTERIOR
A4: Data | B4: Tipo | C4: Valor | D4: Recebido | E4: A receber | F4: cliente | G4: Imposto | I4: Data | J4: Tipo | K4: Valor | L4: Recebido | M4: A receber | N4: cliente | O4: Status
A5: 46176 | B5: Inter | C5: 7000 | E5: 7000 | F5: Naisa | I5: 45988 | J5: Inter | K5: 34240 | L5: 32392 | M5: 1848 | N5: Flávia
A6: 46182 | B6: Caixa | F6: Rafael | I6: 46170 | J6: Inter | K6: 17994 | L6: 14485.2 | M6: 4708.8 | N6: Janaina
A7: 46183 | B7: Local | C7: 2000 | D7: 2000 | E7: - | F7: Iranildes | M7: =SUM(M5:M6) -> 6556.8
A8: 46188 | B8: Local | C8: 2000 | E8: 2000 | F8: Renata
A9: 46192 | B9: Local | C9: 2000 | E9: 2000 | F9: Rafael
A10: 46199 | B10: Local | C10: 2000 | E10: 2000 | F10: Aquiles
A13: TOTAL | C13: =SUM(C5:C12) -> 15000 | D13: =SUM(D5:D12) -> 2000 | E13: =C13-D13 -> 13000
A16: DESPESAS com Pessoal - Diária
A17: Data | B17: Tipo | C17: Valor | D17: Status
A18: 46176 | B18: Diária | C18: 740
A19: 46182 | B19: Diária
A20: 46183 | B20: Diária | C20: 810
A21: 46185 | B21: Diária | C21: 740
A23: TOTAL | C23: =SUM(C14:C22) -> 2290 | D23: =SUM(D14:D22) -> 0 | E23: =C23-D23 -> 2290
A25: DESPESAS com Pessoal - Almoço
A26: Data | B26: Tipo | C26: Valor | D26: Status
A27: 46176 | B27: Almoço | C27: =4*21 -> 84
C34: =SUM(C26:C33) -> 84 | D34: =SUM(D26:D33) -> 0 | E34: =C34-D34 -> 84
C37: =SUM(C18:C36) -> 4748
A40: DESPESAS
A41: MATÉRIA - PRIMA
A42: Data | B42: Tipo | C42: Valor | D42: Pagto
A43: 46185 | D43: Confiança
C50: =SUM(C42:C49) -> 0
A52: COMPRAS - DIVERSAS
A53: Data | B53: Tipo | C53: Valor | D53: Pagto
A54: 46175 | B54: Água | C54: 24 | D54: PIX
A55: 46185 | B55: Água | C55: 24 | D55: PIX
C61: =SUM(C54:C60) -> 48
A63: DESPESAS FIXAS - CONTAS A PAGAR
A64: Data | B64: Tipo | C64: Valor | D64: Status
A65: 46174 | B65: ALUGUEL | C65: 2000 | D65: Pago
A66: 46174 | B66: IPTU | C66: 86.31 | D66: Pago
A67: 46174 | B67: Água | C67: 136.56 | D67: Pago
A68: 46176 | B68: Trafego Pago | C68: 1000 | D68: Pago
A69: 46178 | B69: MASTER FOCO | C69: 1580 | D69: Pago
A70: 46181 | B70: BSOFT | C70: 153.26 | D70: Pago
A71: 46183 | B71: LUZ | C71: 136.75 | D71: Pago
A72: 46181 | B72: Ellen - Contadora | C72: 500 | D72: Pago
A73: 46188 | B73: SEGURO | C73: 644.28 | D73: Pago
A74: 46190 | B74: NET | C74: 409.9
A75: 46191 | B75: Parc Banco | C75: 941.6
A76: 46191 | B76: Div Ativa - DAS
A77: 46193 | B77: DAS | C77: 1350
A78: 46203 | B78: Div Ativa - Alvará
A79: 46203 | B79: SAMMYA | C79: 3000
A80: 46203 | B80: Gasolina - Palio
A81: 46203 | B81: Pro labore | C81: =C13*10% -> 1500
C82: =SUM(C65:C81) -> 13438.66
A84: DESPESAS - FRETE
A85: Data | B85: Tipo | C85: Valor Total | D85: Valor pago | E85: A pagar | F85: Caminhoneiro
A86: 46186 | B86: Frete Naisa | C86: =6*350 -> 2100 | D86: =C86*80% -> 1680 | E86: =C86*20% -> 420 | F86: Cristiano
A87: 46186 | B87: Frete Janaina | C87: =25*350 -> 8750 | D87: =C87*80% -> 7000 | E87: =C87*20% -> 1750 | F87: Cristiano
C91: =SUM(C86:C89) -> 10850 | D91: =SUM(D86:D89) -> 8680 | E91: =SUM(E86:E89) -> 2170
B97: RECEITAS | C97: =C13 -> 15000
B98: DESPESAS | C98: =C50+C61+C82+C91+#REF! -> #REF!
B99: Lucro | C99: =C97-C98 -> #REF!
B100: Davis | C100: =C81+C99 -> #REF!

Sheet Base CR
B1: Data | C1: Mês | D1: Tipo | E1: Valor
A2: 1 | B2: 46024 | C2: =TEXT(B2,"MMM") -> jan | D2: Local | E2: 2000
A3: 2 | B3: 46027 | C3: =TEXT(B3,"MMM") -> jan | D3: Local | E3: 3500
A4: 3 | B4: 46028 | C4: =TEXT(B4,"MMM") -> jan | D4: Local | E4: 2000
A5: 4 | B5: 46028 | C5: =TEXT(B5,"MMM") -> jan | D5: Caixas | E5: 60
A6: 5 | B6: 46029 | C6: =TEXT(B6,"MMM") -> jan | D6: Local | E6: 4000
A7: 6 | B7: 46029 | C7: =TEXT(B7,"MMM") -> jan | D7: Caixas | E7: 24
A8: 7 | B8: 46029 | C8: =TEXT(B8,"MMM") -> jan | D8: Local | E8: 5500
A9: 8 | B9: 46030 | C9: =TEXT(B9,"MMM") -> jan | D9: Caixas | E9: 48
A10: 9 | B10: 46031 | C10: =TEXT(B10,"MMM") -> jan | D10: Local | E10: 2500
A11: 10 | B11: 46034 | C11: =TEXT(B11,"MMM") -> jan | D11: Inter | E11: 12200
A12: 11 | B12: 46034 | C12: =TEXT(B12,"MMM") -> jan | D12: Veiculo | E12: 5000
A13: 12 | B13: 46035 | C13: =TEXT(B13,"MMM") -> jan | D13: Local | E13: 2000
... A81: 81 | B81: 46171 | C81: =TEXT(B81,"MMM") -> mai | D81: Local | E81: 2000
C82: =TEXT(B82,"MMM") -> jan
C83: =TEXT(B83,"MMM") -> jan
C84: =TEXT(B84,"MMM") -> jan
C85: =TEXT(B85,"MMM") -> jan
C86: =TEXT(B86,"MMM") -> jan
C87: =TEXT(B87,"MMM") -> jan

Sheet Base CP
A1: CONTAS A PAGAR 2026
A2: Data | B2: Mês | C2: Descrição | D2: Orçado | E2: Realizado
A3: 46023 | B3: =TEXT(A3,"MMMM") -> janeiro | C3: Aluguel | D3: 2000 | E3: 2000
A4: 46023 | B4: =TEXT(A4,"MMMM") -> janeiro | C4: Agua | D4: 136.56 | E4: 136.56
A5: 46023 | B5: =TEXT(A5,"MMMM") -> janeiro | C5: IPTU | D5: 86.31 | E5: 86.31
A6: 46023 | B6: =TEXT(A6,"MMMM") -> janeiro | C6: Trafego pago | D6: 1000 | E6: 1000
A7: 46027 | B7: =TEXT(A7,"MMMM") -> janeiro | C7: Master Foco | D7: 1580 | E7: 1580
A8: 46027 | B8: =TEXT(A8,"MMMM") -> janeiro | C8: Net | D8: 350
A9: 46027 | B9: =TEXT(A9,"MMMM") -> janeiro | C9: Contabilidade | D9: 400 | E9: 400
A10: 46052 | B10: =TEXT(A10,"MMMM") -> janeiro | C10: Administrativo | D10: 2000 | E10: 2000
A11: 46032 | B11: =TEXT(A11,"MMMM") -> janeiro | C11: Energia Eletrica | D11: 300 | E11: 251.55
A12: 46032 | B12: =TEXT(A12,"MMMM") -> janeiro | C12: Bsoft | D12: 153.26 | E12: 153.26
A13: 46032 | B13: =TEXT(A13,"MMMM") -> janeiro | C13: Empréstimo PF | D13: 941.6 | E13: 941.6
A14: 46037 | B14: =TEXT(A14,"MMMM") -> janeiro | C14: Seguro | D14: 644.28 | E14: 400
A15: 46042 | B15: =TEXT(A15,"MMMM") -> janeiro | C15: DAS | D15: 1000 | E15: =JANEIRO!C96 -> 1691.83
A16: 46052 | B16: =TEXT(A16,"MMMM") -> janeiro | C16: Div Ativa - DAS | D16: 485.76 | E16: 485.76
A17: 46054 | B17: =TEXT(A17,"MMMM") -> fevereiro | C17: Aluguel | D17: 2000 | E17: 2000
A18: 46054 | B18: =TEXT(A18,"MMMM") -> fevereiro | C18: Agua | D18: 136.56 | E18: 136.56
A19: 46054 | B19: =TEXT(A19,"MMMM") -> fevereiro | C19: IPTU | D19: 86.31 | E19: 86.31
A20: 46054 | B20: =TEXT(A20,"MMMM") -> fevereiro | C20: Trafego pago | D20: 1000 | E20: 1000
A21: 46058 | B21: =TEXT(A21,"MMMM") -> fevereiro | C21: Master Foco | D21: 1580 | E21: 1580
A22: 46058 | B22: =TEXT(A22,"MMMM") -> fevereiro | C22: Net | D22: 350
A23: 46058 | B23: =TEXT(A23,"MMMM") -> fevereiro | C23: Contabilidade | D23: 400 | E23: 400
A24: 46081 | B24: =TEXT(A24,"MMMM") -> fevereiro | C24: Administrativo | D24: 3000 | E24: 3000
A25: 46063 | B25: =TEXT(A25,"MMMM") -> fevereiro | C25: Energia Eletrica | D25: 300 | E25: 223.23
A26: 46063 | B26: =TEXT(A26,"MMMM") -> fevereiro | C26: Bsoft | D26: 153.26 | E26: 153.26
A27: 46063 | B27: =TEXT(A27,"MMMM") -> fevereiro | C27: Empréstimo PF | D27: 941.6 | E27: 941.6
A28: 46068 | B28: =TEXT(A28,"MMMM") -> fevereiro | C28: Seguro | D28: 644.28 | E28: 644.28
A29: 46073 | B29: =TEXT(A29,"MMMM") -> fevereiro | C29: DAS | D29: 1000 | E29: =FEVEREIRO!C100 -> 0
A30: 46081 | B30: =TEXT(A30,"MMMM") -> fevereiro | C30: Div Ativa - DAS | D30: 485.76 | E30: 496.26
A31: 46082 | B31: =TEXT(A31,"MMMM") -> março | C31: Aluguel | D31: 2000 | E31: 2000
A32: 46082 | B32: =TEXT(A32,"MMMM") -> março | C32: Agua | D32: 136.56 | E32: 136.56
A33: 46082 | B33: =TEXT(A33,"MMMM") -> março | C33: IPTU | D33: 86.31 | E33: 86.31
A34: 46082 | B34: =TEXT(A34,"MMMM") -> março | C34: Trafego pago | D34: 1000 | E34: 1000
A35: 46086 | B35: =TEXT(A35,"MMMM") -> março | C35: Net | D35: 350
A36: 46086 | B36: =TEXT(A36,"MMMM") -> março | C36: Master Foco | D36: 1580 | E36: 1580
A37: 46086 | B37: =TEXT(A37,"MMMM") -> março | C37: Contabilidade | D37: 400 | E37: 400
A38: 46111 | B38: =TEXT(A38,"MMMM") -> março | C38: Administrativo | D38: 3000 | E38: 3000
A39: 46091 | B39: =TEXT(A39,"MMMM") -> março | C39: Energia Eletrica | D39: 300 | E39: 186.16
A40: 46091 | B40: =TEXT(A40,"MMMM") -> março | C40: Bsoft | D40: 153.26 | E40: 153.26
A41: 46091 | B41: =TEXT(A41,"MMMM") -> março | C41: Empréstimo PF | D41: 941.6 | E41: 941.6
A42: 46096 | B42: =TEXT(A42,"MMMM") -> março | C42: Seguro | D42: 644.28 | E42: 644.28
A43: 46101 | B43: =TEXT(A43,"MMMM") -> março | C43: Div Ativa - Alvará | D43: 310.24 | E43: 310.24
A44: 46101 | B44: =TEXT(A44,"MMMM") -> março | C44: DAS | D44: 1000 | E44: =MARÇO!C98 -> 1448
A45: 46111 | B45: =TEXT(A45,"MMMM") -> março | C45: Div Ativa - DAS | D45: 485.76
A46: 46113 | B46: =TEXT(A46,"MMMM") -> abril | C46: Aluguel | D46: 2000 | E46: 2000
A47: 46113 | B47: =TEXT(A47,"MMMM") -> abril | C47: Agua | D47: 136.56 | E47: 136.56
A48: 46113 | B48: =TEXT(A48,"MMMM") -> abril | C48: IPTU | D48: 86.31 | E48: 86.31
A49: 46113 | B49: =TEXT(A49,"MMMM") -> abril | C49: Trafego pago | D49: 1000 | E49: 1000
A50: 46117 | B50: =TEXT(A50,"MMMM") -> abril | C50: Net | D50: 350 | E50: 425.38
A51: 46117 | B51: =TEXT(A51,"MMMM") -> abril | C51: Master Foco | D51: 1580 | E51: 1580
A52: 46117 | B52: =TEXT(A52,"MMMM") -> abril | C52: Contabilidade | D52: 400 | E52: 400
A53: 46142 | B53: =TEXT(A53,"MMMM") -> abril | C53: Administrativo | D53: 3000 | E53: 3000
A54: 46122 | B54: =TEXT(A54,"MMMM") -> abril | C54: Energia Eletrica | D54: 300 | E54: =ABRIL!C69 -> 181.06
A55: 46122 | B55: =TEXT(A55,"MMMM") -> abril | C55: Bsoft | D55: 153.26 | E55: 153.26
A56: 46122 | B56: =TEXT(A56,"MMMM") -> abril | C56: Empréstimo PF | D56: 941.6 | E56: 941.6
A57: 46127 | B57: =TEXT(A57,"MMMM") -> abril | C57: Seguro | D57: 644.28 | E57: 644.28
A58: 46132 | B58: =TEXT(A58,"MMMM") -> abril | C58: Div Ativa - Alvará | D58: 310.24 | E58: 313.37
A59: 46132 | B59: =TEXT(A59,"MMMM") -> abril | C59: DAS | D59: 1000 | E59: =ABRIL!C74 -> 2947.28
A60: 46142 | B60: =TEXT(A60,"MMMM") -> abril | C60: Div Ativa - DAS | D60: 485.76 | E60: 506.99
A61: 46142 | B61: =TEXT(A61,"MMMM") -> abril | C61: Sistema Financeiro | D61: 100 | E61: 100
A62: 46143 | B62: =TEXT(A62,"MMMM") -> maio | C62: Aluguel | D62: 2000 | E62: 2000
A63: 46143 | B63: =TEXT(A63,"MMMM") -> maio | C63: Agua | D63: 136.56 | E63: 136.56
A64: 46143 | B64: =TEXT(A64,"MMMM") -> maio | C64: IPTU | D64: 86.31 | E64: 86.31
A65: 46143 | B65: =TEXT(A65,"MMMM") -> maio | C65: Trafego pago | D65: 1000 | E65: 1000
A66: 46147 | B66: =TEXT(A66,"MMMM") -> maio | C66: Net | D66: 350
A67: 46147 | B67: =TEXT(A67,"MMMM") -> maio | C67: Master Foco | D67: 1580 | E67: 1580
A68: 46147 | B68: =TEXT(A68,"MMMM") -> maio | C68: Contabilidade | D68: 400 | E68: 400
A69: 46172 | B69: =TEXT(A69,"MMMM") -> maio | C69: Administrativo | D69: 3000 | E69: 3000
A70: 46152 | B70: =TEXT(A70,"MMMM") -> maio | C70: Energia Eletrica | D70: 300 | E70: =MAIO!C78 -> 173.82
A71: 46152 | B71: =TEXT(A71,"MMMM") -> maio | C71: Bsoft | D71: 153.26 | E71: 153.26
A72: 46152 | B72: =TEXT(A72,"MMMM") -> maio | C72: Empréstimo PF | D72: 941.6 | E72: 941.6
A73: 46157 | B73: =TEXT(A73,"MMMM") -> maio | C73: Seguro | D73: 644.28 | E73: 644.28
A74: 46162 | B74: =TEXT(A74,"MMMM") -> maio | C74: Div Ativa - Alvará | D74: 310.24
A75: 46162 | B75: =TEXT(A75,"MMMM") -> maio | C75: DAS | D75: 1000 | E75: =MAIO!C84 -> 432.96
A76: 46172 | B76: =TEXT(A76,"MMMM") -> maio | C76: Div Ativa - DAS | D76: 485.76 | E76: 512.29
A77: 46172 | B77: =TEXT(A77,"MMMM") -> maio | C77: Sistema Financeiro | D77: 100
A78: 46174 | B78: =TEXT(A78,"MMMM") -> junho | C78: Aluguel | D78: 2000 | E78: 2000
A79: 46174 | B79: =TEXT(A79,"MMMM") -> junho | C79: Agua | D79: 136.56 | E79: 136.56
A80: 46174 | B80: =TEXT(A80,"MMMM") -> junho | C80: IPTU | D80: 86.31 | E80: 86.31
A81: 46174 | B81: =TEXT(A81,"MMMM") -> junho | C81: Trafego pago | D81: 1000
A82: 46178 | B82: =TEXT(A82,"MMMM") -> junho | C82: Net | D82: 350
A83: 46178 | B83: =TEXT(A83,"MMMM") -> junho | C83: Master Foco | D83: 1580 | E83: 1580
A84: 46178 | B84: =TEXT(A84,"MMMM") -> junho | C84: Contabilidade | D84: 400 | E84: 500
A85: 46203 | B85: =TEXT(A85,"MMMM") -> junho | C85: Administrativo | D85: 3000
A86: 46183 | B86: =TEXT(A86,"MMMM") -> junho | C86: Energia Eletrica | D86: 300 | E86: =JUNHO!C71 -> 136.75
A87: 46183 | B87: =TEXT(A87,"MMMM") -> junho | C87: Bsoft | D87: 153.26 | E87: 153.26
A88: 46183 | B88: =TEXT(A88,"MMMM") -> junho | C88: Empréstimo PF | D88: 941.6
A89: 46188 | B89: =TEXT(A89,"MMMM") -> junho | C89: Seguro | D89: 644.28
A90: 46193 | B90: =TEXT(A90,"MMMM") -> junho | C90: Div Ativa - Alvará | D90: 310.24
A91: 46193 | B91: =TEXT(A91,"MMMM") -> junho | C91: DAS | D91: 1000
A92: 46203 | B92: =TEXT(A92,"MMMM") -> junho | C92: Div Ativa - DAS | D92: 485.76
A93: 46203 | B93: =TEXT(A93,"MMMM") -> junho | C93: Sistema Financeiro | D93: 100
A94: 46204 | B94: =TEXT(A94,"MMMM") -> julho | C94: Aluguel | D94: 2000
A95: 46204 | B95: =TEXT(A95,"MMMM") -> julho | C95: Agua | D95: 136.56
A96: 46204 | B96: =TEXT(A96,"MMMM") -> julho | C96: IPTU | D96: 86.31
A97: 46204 | B97: =TEXT(A97,"MMMM") -> julho | C97: Trafego pago | D97: 1000
A98: 46208 | B98: =TEXT(A98,"MMMM") -> julho | C98: Net | D98: 350
A99: 46208 | B99: =TEXT(A99,"MMMM") -> julho | C99: Master Foco | D99: 1580
... A189: 46386 | B189: =TEXT(A189,"MMMM") -> dezembro | C189: Sistema Financeiro | D189: 100
...

Sheet Detalhes1
A1: Detalhes do DBR MUDANÇAS 2026 - Tipo: Guarda-móveis, Mês: fev
A3: Data | B3: Mês | C3: Tipo | D3: Valor
A4: 46063 | B4: fev | C4: Guarda-móveis | D4: 2000

Sheet Din_CR
A3: DBR MUDANÇAS 2026
A4: FATURAMENTO | B4: Janeiro | C4: Fevereiro | D4: Março | E4: Abril | F4: Maio | G4: Total Geral
A5: Caixas | B5: 9069.5 | C5: 291 | D5: 54 | E5: 6400 | G5: 15814.5
A6: Frete | B6: 500 | D6: 1200 | G6: 1700
A7: Inter | B7: 28340 | C7: 50140 | D7: 67362 | E7: 7000 | F7: 17994 | G7: 170836
A8: Local | B8: 34600 | C8: 42650 | D8: 46150 | E8: 15500 | F8: 24936 | G8: 163836
A9: Veiculo | B9: 5000 | C9: 10200 | G9: 15200
A10: Guarda-móveis | B10: 700 | C10: 2000 | G10: 2700
A11: Total Geral | B11: 78209.5 | C11: 105281 | D11: 114766 | E11: 28900 | F11: 42930 | G11: 370086.5
A13: DBR Mudanças 2026
A14: Quantidade | B14: Janeiro | C14: Fevereiro | D14: Março | E14: Abril | F14: Maio | G14: Total Geral
A15: Caixas | B15: 4 | C15: 4 | D15: 2 | E15: 1 | G15: 11
A16: Frete | B16: 1 | D16: 1 | G16: 2
A17: Inter | B17: 3 | C17: 3 | D17: 2 | E17: 1 | F17: 1 | G17: 10
A18: Local | B18: 13 | C18: 8 | D18: 15 | E18: 6 | F18: 10 | G18: 52
A19: Veiculo | B19: 1 | C19: 2 | G19: 3
A20: Guarda-móveis | B20: 1 | C20: 1 | G20: 2
A21: Total Geral | B21: 23 | C21: 18 | D21: 20 | E21: 8 | F21: 11 | G21: 80

Sheet Din_CP
A3: Contas a Pagar | B3: Orçado | C3: Realizado
A4: janeiro | B4: 28397.77 | C4: 46996.87
A5: fevereiro | B5: 30947.77 | C5: 52631.5
A6: março | B6: 31388.01 | C6: 11886.41
A7: abril | B7: 31488.01 | C7: 14416.09
A8: maio | B8: 22663.01 | C8: 21686.08
A9: junho | B9: 31488.01 | C9: 13272.88
A10: julho | B10: 31488.01
A11: agosto | B11: 31488.01
A12: setembro | B12: 31488.01
A13: outubro | B13: 31488.01
A14: novembro | B14: 31488.01
A15: dezembro | B15: 31488.01
A16: Total Geral | B16: 365300.64 | C16: 160889.83
A19: REALIZADO
A20: Contas a Pagar | B20: JANEIRO | C20: FEVEREIRO | D20: MARÇO | E20: ABRIL | F20: MAIO | G20: JUNHO | H20: JULHO | I20: AGOSTO | J20: SETEMBRO | K20: OUTUBRO | L20: NOVEMBRO | M20: DEZEMBRO | N20: TOTAL GERAL
A21: Administrativo | B21: 2000 | C21: 3000 | D21: 3000 | E21: 3000 | F21: 3000 | N21: 14000
A22: Agua | B22: 136.56 | C22: 136.56 | D22: 136.56 | E22: 136.56 | F22: 136.56 | G22: 136.56 | N22: 819.36
A23: Almoço | B23: 1720 | C23: 1870 | F23: 1265 | N23: 4855
A24: Aluguel | B24: 2000 | C24: 2000 | D24: 2000 | E24: 2000 | F24: 2000 | G24: 2000 | N24: 12000
A25: Bsoft | B25: 153.26 | C25: 153.26 | D25: 153.26 | E25: 153.26 | F25: 153.26 | G25: 153.26 | N25: 919.56
A26: Contabilidade | B26: 400 | C26: 400 | D26: 400 | E26: 400 | F26: 400 | G26: 500 | N26: 2500
A27: DAS | B27: 1691.83 | C27: 0 | D27: 1448 | E27: 2947.28 | F27: 432.96 | N27: 6520.07
A28: Diária | B28: 15600 | C28: 17000 | F28: 8910 | N28: 41510
A29: Div Ativa - Alvará | D29: 310.24 | E29: 313.37 | N29: 623.61
A30: Div Ativa - DAS | B30: 485.76 | C30: 496.26 | E30: 506.99 | F30: 512.29 | N30: 2001.3
A31: Empréstimo PF | B31: 941.6 | C31: 941.6 | D31: 941.6 | E31: 941.6 | F31: 941.6 | N31: 4708
A32: Energia Eletrica | B32: 251.55 | C32: 223.23 | D32: 186.16 | E32: 181.06 | F32: 173.82 | G32: 136.75 | N32: 1152.57
A33: Frete Inter | B33: 18550 | C33: 23100 | F33: 450 | G33: 8680 | N33: 50780
A34: IPTU | B34: 86.31 | C34: 86.31 | D34: 86.31 | E34: 86.31 | F34: 86.31 | G34: 86.31 | N34: 517.86
A35: Master Foco | B35: 1580 | C35: 1580 | D35: 1580 | E35: 1580 | F35: 1580 | G35: 1580 | N35: 9480
A36: Net | E36: 425.38 | N36: 425.38
A37: Seguro | B37: 400 | C37: 644.28 | D37: 644.28 | E37: 644.28 | F37: 644.28 | N37: 2977.12
A38: Sistema Financeiro | E38: 100 | N38: 100
A39: Trafego pago | B39: 1000 | C39: 1000 | D39: 1000 | E39: 1000 | F39: 1000 | N39: 5000
A40: TOTAL GERAL | B40: 46996.87 | C40: 52631.5 | D40: 11886.41 | E40: 14416.09 | F40: 21686.08 | G40: 13272.88 | N40: 160889.83

Sheet Contas a Pagar
A1: DBR MUDANÇAS - CONTAS A PAGAR 2026
B3: Dia Vcto | C3: Orçado | D3: Realizado | E3: Orçado | F3: Realizado | G3: Orçado | H3: Realizado | I3: Orçado | J3: Realizado | K3: Orçado | L3: Realizado | M3: Orçado | N3: Realizado | O3: Orçado | P3: Realizado | Q3: Orçado | R3: Realizado | S3: Orçado | T3: Realizado | U3: Orçado | V3: Realizado | W3: Orçado | X3: Realizado | Y3: Orçado | Z3: Realizado | AA3: Orçado | AB3: Realizado
A4: Contas a Pagar 2026 | C4: JANEIRO | E4: FEVEREIRO | G4: MARÇO | I4: ABRIL | K4: MAIO | M4: JUNHO | O4: JULHO | Q4: AGOSTO | S4: SETEMBRO | U4: OUTUBRO | W4: NOVEMBRO | Y4: DEZEMBRO | AA4: TOTAL | AB4: TOTAL
A5: Aluguel | B5: 1 | C5: 2000 | D5: 2000 | E5: 2000 | F5: 2000 | G5: 2000 | H5: 2000 | I5: 2000 | J5: 2212 | K5: 2000 | L5: 2212 | M5: 2000 | O5: 2000 | Q5: 2000 | S5: 2000 | U5: 2000 | W5: 2000 | Y5: 2000 | AA5: =SUM(C5+E5+G5+I5+K5+M5+O5+Q5+S5+U5+W5+Y5) -> 24000 | AB5: =D5+F5+H5+J5+L5+N5+P5+R5+T5+V5+X5+Z5 -> 10424
A6: Água | B6: 1 | C6: 136.56 | D6: 136.56 | E6: 136.56 | F6: 136.56 | G6: 136.56 | H6: 136.56 | I6: 136.56 | K6: 136.56 | M6: 136.56 | O6: 136.56 | Q6: 136.56 | S6: 136.56 | U6: 136.56 | W6: 136.56 | Y6: 136.56 | AA6: =SUM(C6+E6+G6+I6+K6+M6+O6+Q6+S6+U6+W6+Y6) -> 1638.72
A7: IPTU | B7: 1 | C7: 86.31 | D7: 86.31 | E7: 86.31 | F7: 86.31 | G7: 86.31 | H7: 86.31 | I7: 86.31 | K7: 86.31 | M7: 86.31 | O7: 86.31 | Q7: 86.31 | S7: 86.31 | U7: 86.31 | W7: 86.31 | Y7: 86.31 | AA7: =SUM(C7+E7+G7+I7+K7+M7+O7+Q7+S7+U7+W7+Y7) -> 1035.72
A8: Bsoft | B8: 4 | C8: 106.57 | D8: 153.26 | E8: 153.26 | F8: 153.26 | G8: 153.26 | H8: 153.26 | I8: 153.26 | K8: 153.26 | M8: 153.26 | O8: 153.26 | Q8: 153.26 | S8: 153.26 | U8: 153.26 | W8: 153.26 | Y8: 153.26 | AA8: =SUM(C8+E8+G8+I8+K8+M8+O8+Q8+S8+U8+W8+Y8) -> 1792.43 | AB8: =D8+F8+H8+J8+L8+N8+P8+R8+T8+V8+X8+Z8 -> 459.78
A9: Master Foco | B9: 5 | C9: 1580 | D9: 1580 | E9: 1580 | F9: 1580 | G9: 1580 | H9: 1580 | I9: 1580 | K9: 1580 | M9: 1580 | O9: 1580 | Q9: 1580 | S9: 1580 | U9: 1580 | W9: 1580 | Y9: 1580 | AA9: =SUM(C9+E9+G9+I9+K9+M9+O9+Q9+S9+U9+W9+Y9) -> 18960 | AB9: =D9+F9+H9+J9+L9+N9+P9+R9+T9+V9+X9+Z9 -> 4740
A10: Banco | B10: 17 | C10: 941.6 | D10: 941.6 | E10: 941.6 | F10: 941.6 | G10: 941.6 | H10: 941.6 | I10: 941.6 | K10: 941.6 | M10: 941.6 | O10: 941.6 | Q10: 0 | S10: 0 | U10: 0 | W10: 0 | Y10: 0 | AA10: =SUM(C10+E10+G10+I10+K10+M10+O10+Q10+S10+U10+W10+Y10) -> 6591.2 | AB10: =D10+F10+H10+J10+L10+N10+P10+R10+T10+V10+X10+Z10 -> 2824.8
A11: Energia Eletrica | B11: 10 | C11: 300 | D11: 251.55 | E11: 300 | F11: 223.23 | G11: 300 | H11: 186.16 | I11: 300 | K11: 300 | M11: 300 | O11: 300 | Q11: 300 | S11: 300 | U11: 300 | W11: 300 | Y11: 300 | AA11: =SUM(C11+E11+G11+I11+K11+M11+O11+Q11+S11+U11+W11+Y11) -> 3600 | AB11: =D11+F11+H11+J11+L11+N11+P11+R11+T11+V11+X11+Z11 -> 660.94
A12: Net/ Celular | B12: 10 | C12: 350 | E12: 350 | G12: 350 | I12: 350 | J12: 425.38 | K12: 425.38 | M12: 425.38 | O12: 350 | Q12: 350 | S12: 350 | U12: 350 | W12: 350 | Y12: 350 | AA12: =SUM(C12+E12+G12+I12+K12+M12+O12+Q12+S12+U12+W12+Y12) -> 4350.76 | AB12: =D12+F12+H12+J12+L12+N12+P12+R12+T12+V12+X12+Z12 -> 425.38
A13: Div Ativa - Alvará | B13: 15 | C13: 0 | D13: 0 | E13: 0 | F13: 0 | G13: 310.24 | H13: 310.24 | I13: 295.11 | K13: 295.11 | M13: 295.11 | O13: 295.11 | Q13: 295.11 | S13: 295.11 | U13: 295.11 | W13: 295.11 | Y13: 295.11 | AA13: =SUM(C13+E13+G13+I13+K13+M13+O13+Q13+S13+U13+W13+Y13) -> 2966.23 | AB13: =D13+F13+H13+J13+L13+N13+P13+R13+T13+V13+X13+Z13 -> 310.24
A14: Seguro | B14: 15 | C14: 644.28 | D14: 644.28 | E14: 644.28 | F14: 644.28 | G14: 644.28 | H14: 644.28 | I14: 644.28 | K14: 644.28 | M14: 644.28 | O14: 644.28 | Q14: 644.28 | S14: 644.28 | U14: 644.28 | W14: 644.28 | Y14: 644.28 | AA14: =SUM(C14+E14+G14+I14+K14+M14+O14+Q14+S14+U14+W14+Y14) -> 7731.36
A15: DAS | B15: 20 | C15: 1400 | D15: 1691.83 | E15: 1400 | F15: 1185.95 | G15: 1400 | H15: 1448 | I15: 1400 | K15: 1400 | L15: 432.96 | M15: 1400 | O15: 1400 | Q15: 1400 | S15: 1400 | U15: 1400 | W15: 1400 | Y15: 1400 | AA15: =SUM(C15+E15+G15+I15+K15+M15+O15+Q15+S15+U15+W15+Y15) -> 16800 | AB15: =D15+F15+H15+J15+L15+N15+P15+R15+T15+V15+X15+Z15 -> 4758.74
A16: Div Ativa - DAS | B16: 30 | C16: 485.76 | D16: 485.76 | E16: 485.76 | F16: 496.26 | G16: 485.76 | I16: 485.76 | K16: 485.76 | M16: 485.76 | O16: 485.76 | Q16: 485.76 | S16: 485.76 | U16: 485.76 | W16: 485.76 | Y16: 485.76 | AA16: =SUM(C16+E16+G16+I16+K16+M16+O16+Q16+S16+U16+W16+Y16) -> 5829.12 | AB16: =D16+F16+H16+J16+L16+N16+P16+R16+T16+V16+X16+Z16 -> 982.02
A17: Trafego pago | B17: 30 | C17: 1000 | D17: 1000 | E17: 1000 | F17: 2000 | G17: 1000 | I17: 1000 | K17: 1000 | M17: 1000 | O17: 1000 | Q17: 1000 | S17: 1000 | U17: 1000 | W17: 1000 | Y17: 1000 | AA17: =SUM(C17+E17+G17+I17+K17+M17+O17+Q17+S17+U17+W17+Y17) -> 12000 | AB17: =D17+F17+H17+J17+L17+N17+P17+R17+T17+V17+X17+Z17 -> 3000
A18: Sistema Airton | B18: 30 | I18: 100 | J18: 100 | K18: 100 | M18: 100 | O18: 100 | Q18: 100 | S18: 100 | U18: 100 | W18: 100 | Y18: 100 | AA18: =SUM(C18+E18+G18+I18+K18+M18+O18+Q18+S18+U18+W18+Y18) -> 900
A19: Alvará 2026 | C19: 0 | D19: 0 | E19: 200 | F19: 182.92 | G19: 0 | I19: 0 | K19: 0 | M19: 0 | O19: - | Q19: - | S19: - | U19: - | W19: 0 | Y19: 0 | AA19: =C19+E19 -> 200 | AB19: =D19+F19+H19+J19+L19+N19+P19+R19+T19+V19+X19+Z19 -> 182.92
A20: Certificado Digital | AA20: =SUM(C20+E20+G20+I20+K20+M20+O20+Q20+S20+U20+W20+Y20) -> 0
A21: IPVA Caminhão 7436 | AA21: =SUM(C21+E21+G21+I21+K21+M21+O21+Q21+S21+U21+W21+Y21) -> 0
A22: IPVA Ranger 0D55 | AA22: =SUM(C22+E22+G22+I22+K22+M22+O22+Q22+S22+U22+W22+Y22) -> 0
A23: IPVA Palio 1067 | AA23: =SUM(C23+E23+G23+I23+K23+M23+O23+Q23+S23+U23+W23+Y23) -> 0
A24: TOTAL | C24: =SUM(C5:C23) -> 9031.08 | D24: =SUM(D5:D23) -> 8971.15 | E24: =SUM(E5:E23) -> 9277.77 | F24: =SUM(F5:F23) -> 9630.37 | G24: =SUM(G5:G23) -> 9388.01 | H24: =SUM(H5:H23) -> 7486.41 | I24: =SUM(I5:I23) -> 9472.88 | J24: =SUM(J5:J23) -> 2737.38 | ... Z24: =SUM(Z5:Z23) -> 0 | AA24: =SUM(AA5:AA19) -> 108395.54 | AB24: =SUM(AB5:AB19) -> 28768.82
